{
  "about": {
    "title": "About",
    "text": "M37 is a podcast about the present and the future of technology."
  },
  "layout": {
    "announcementBar": {
      "text": "Subscribe now on Apple Podcasts"
    },
    "navBar": {
      "links": [
        {
          "name": "About",
          "path": "/about"
        },
        {
          "name": "Episodes",
          "path": "/episodes"
        },
        {
          "name": "Subscribe Now",
          "path": "http://google.com",
          "primary": true
        }
      ]
    },
    "footer": {
      "text": "Movimiento 37",
      "links": [
        {
          "name": "Spotify",
          "path": "http://something."
        },
        {
          "name": "Apple Podcast",
          "path": "http://something."
        },
        {
          "name": "Google Play",
          "path": "http://something."
        }
      ]
    }
  }
}
